roboball2d/__init__.py
roboball2d/factory.py
roboball2d/item.py
roboball2d/utils.py
roboball2d/ball/__init__.py
roboball2d/ball/ball_config.py
roboball2d/ball_gun/__init__.py
roboball2d/ball_gun/default_ball_gun.py
roboball2d/ball_gun/drop_ball_gun.py
roboball2d/demos/__init__.py
roboball2d/demos/balls.py
roboball2d/demos/mirror_balls.py
roboball2d/demos/mirroring.py
roboball2d/demos/rendering.py
roboball2d/demos/rendering_callback.py
roboball2d/demos/simple.py
roboball2d/physics/__init__.py
roboball2d/physics/b2_robot.py
roboball2d/physics/b2_world.py
roboball2d/physics/default_b2_robot.py
roboball2d/physics/world_state.py
roboball2d/rendering/__init__.py
roboball2d/rendering/pyglet_renderer.py
roboball2d/rendering/pyglet_utils.py
roboball2d/rendering/rendering_config.py
roboball2d/robot/__init__.py
roboball2d/robot/default_robot_config.py
roboball2d/robot/default_robot_state.py
roboball2d/robot/pd_controller.py
roboball2d/robot/robot_config.py
roboball2d/robot/robot_state.py
roboball2d-0.1.7.data/scripts/roboball2d_balls_demo
roboball2d-0.1.7.data/scripts/roboball2d_demo
roboball2d-0.1.7.data/scripts/roboball2d_mirror_balls_demo
roboball2d-0.1.7.data/scripts/roboball2d_mirror_demo
roboball2d-0.1.7.data/scripts/roboball2d_rendering_demo
tests/__init__.py
tests/test_bounces.py
tests/test_demos.py
tests/test_import.py
roboball2d-0.1.7.dist-info/LICENSE
roboball2d-0.1.7.dist-info/METADATA
roboball2d-0.1.7.dist-info/WHEEL
roboball2d-0.1.7.dist-info/top_level.txt
roboball2d-0.1.7.dist-info/RECORD
