Metadata-Version: 2.1
Name: roboball2d
Version: 0.1.7
Summary: A simulated 2d robot playing with balls
Home-page: https://github.com/intelligent-soft-robots/roboball2d
Author: Nico Gürtler, Vincent Berenz
Author-email: nico.guertler@tuebingen.mpg.de, vberenz@tuebingen.mpg.de
License: UNKNOWN
Platform: UNKNOWN
Requires-Dist: box2d-py
Requires-Dist: numpy
Requires-Dist: pyglet
